codeforces_client/__init__.py
codeforces_client/__main__.py
codeforces_client/api/__init__.py
codeforces_client/api/client.py
codeforces_client/api/contest.py
codeforces_client/api/exceptions.py
codeforces_client/api/problem.py
codeforces_client/api/submission.py
codeforces_client/api/verdict.py
codeforces_client/commands/__init__.py
codeforces_client/commands/config.py
codeforces_client/commands/load.py
codeforces_client/utils/__init__.py
codeforces_client/utils/auto_name_enum.py
codeforces_client/utils/lang2ext.py
codeforces_client-0.0.10.dist-info/LICENSE
codeforces_client-0.0.10.dist-info/METADATA
codeforces_client-0.0.10.dist-info/WHEEL
codeforces_client-0.0.10.dist-info/entry_points.txt
codeforces_client-0.0.10.dist-info/top_level.txt
codeforces_client-0.0.10.dist-info/RECORD
