Metadata-Version: 2.1
Name: codeforces-client
Version: 0.0.10
Summary: Codeforces Client is a Python library and tooling for working with Codeforces.
Home-page: https://github.com/sofigern/codeforces
Author: Mykola Mostovenko
Author-email: sofigenr@gmail.com
License: UNKNOWN
Project-URL: Bug Tracker, https://github.com/sofigern/codeforces/issues
Platform: UNKNOWN
Classifier: Programming Language :: Python :: 3
Classifier: Operating System :: OS Independent
Requires-Python: >=3.9
License-File: LICENSE
